cd_connector_hub/__init__.py
cd_connector_hub/kafka_connector.py
cd_connector_hub/py.typed
cd_connector_hub-0.1.4.dist-info/WHEEL
cd_connector_hub-0.1.4.dist-info/METADATA
cd_connector_hub-0.1.4.dist-info/RECORD
