Metadata-Version: 2.3
Name: cd-connector-hub
Version: 0.1.4
Summary: Add your description here
Requires-Dist: confluent-kafka>=2.11.1
Requires-Python: >=3.13
